{"name":"validar campos obligatorios completos","id":"validacion-de-campos-del-formulario;validar-campos-obligatorios-completos","testSteps":[{"number":1,"description":"Dado Que me encuentro en la opcion de reserva","duration":8658,"startTime":"2022-04-28T12:53:18.180-05:00[America/Bogota]","screenshots":[{"screenshot":"0e4998cd9bbd8e674ceb6a5f56f3b71b626c92977ceda08c0e7e70491b20a782.png","timeStamp":1651168406838}],"result":"SUCCESS","precondition":false,"level":0,"children":[{"number":2,"description":"Student open landing page","duration":2563,"startTime":"2022-04-28T12:53:23.581-05:00[America/Bogota]","screenshots":[{"screenshot":"74e472173ebcd3031c5687cd3809822ebbe405c571caf98e0c1dc26176ce91b7.png","timeStamp":1651168404277},{"screenshot":"0e4998cd9bbd8e674ceb6a5f56f3b71b626c92977ceda08c0e7e70491b20a782.png","timeStamp":1651168406144}],"result":"SUCCESS","precondition":false,"level":1,"children":[{"number":3,"description":"Student opens the Landing page","duration":1819,"startTime":"2022-04-28T12:53:24.298-05:00[America/Bogota]","screenshots":[{"screenshot":"74e472173ebcd3031c5687cd3809822ebbe405c571caf98e0c1dc26176ce91b7.png","timeStamp":1651168404322},{"screenshot":"0e4998cd9bbd8e674ceb6a5f56f3b71b626c92977ceda08c0e7e70491b20a782.png","timeStamp":1651168406116}],"result":"SUCCESS","precondition":false,"level":2}]},{"number":4,"description":"Student naverga a foodka","duration":658,"startTime":"2022-04-28T12:53:26.158-05:00[America/Bogota]","screenshots":[{"screenshot":"0e4998cd9bbd8e674ceb6a5f56f3b71b626c92977ceda08c0e7e70491b20a782.png","timeStamp":1651168406797},{"screenshot":"0e4998cd9bbd8e674ceb6a5f56f3b71b626c92977ceda08c0e7e70491b20a782.png","timeStamp":1651168406816}],"result":"SUCCESS","precondition":false,"level":1}]},{"number":5,"description":"Cuando lleno la informacion en los campos obligatorios y doy click en el boton Guardar reserva","duration":35149,"startTime":"2022-04-28T12:53:26.839-05:00[America/Bogota]","screenshots":[{"screenshot":"d86c064db4f706e798362da89e2388c705ec0fc146d28d4b601d3d8333f5a38b.png","timeStamp":1651168441988}],"result":"SUCCESS","precondition":false,"level":0,"children":[{"number":6,"description":"Student crear nueva reserva","duration":33511,"startTime":"2022-04-28T12:53:27.724-05:00[America/Bogota]","screenshots":[{"screenshot":"283a6d7221a748c74c4589ae6713676c687d695735d2bcf0130c09d931c73ac0.png","timeStamp":1651168441235}],"result":"SUCCESS","precondition":false,"level":1,"children":[{"number":7,"description":"Student clicks on BtnCrearReserva","duration":2032,"startTime":"2022-04-28T12:53:28.501-05:00[America/Bogota]","screenshots":[{"screenshot":"450bb16fee49ebb337310f922cb01ec974b9a22dd8a482efa62d0334a2c62948.png","timeStamp":1651168409163},{"screenshot":"3d85b0c377b3aadefc8e72e1a45e95bfba21ae0392efc2b3edd53c0ac0b83021.png","timeStamp":1651168410533}],"result":"SUCCESS","precondition":false,"level":2},{"number":8,"description":"Student clicks on BtnCalendario","duration":1950,"startTime":"2022-04-28T12:53:30.652-05:00[America/Bogota]","screenshots":[{"screenshot":"659f1cbe6e99d7631a07b8c676b9e8d9b9c7b2d77c6e992637eea58264101dfa.png","timeStamp":1651168411408},{"screenshot":"b37a1a6f53f87e0852a88db507da81900ae51c6c8de72c0fb29ddc0560a9d5fe.png","timeStamp":1651168412602}],"result":"SUCCESS","precondition":false,"level":2},{"number":9,"description":"Student clicks on BtnDiaFecha","duration":2192,"startTime":"2022-04-28T12:53:32.731-05:00[America/Bogota]","screenshots":[{"screenshot":"777124bb7e12918364363375a80b05711b9701da8c72e2a19f7d86129bbe65d8.png","timeStamp":1651168413520},{"screenshot":"fae913728ab32918eab79fa5e082f2805e88adf8b6f6354f768a62fa023758dd.png","timeStamp":1651168414923}],"result":"SUCCESS","precondition":false,"level":2},{"number":10,"description":"Student clicks on BtnNext","duration":2249,"startTime":"2022-04-28T12:53:35.053-05:00[America/Bogota]","screenshots":[{"screenshot":"170bfda6fca3715e0b3b79b9999f33fde93b684ee88dafd5e8f36da739f83612.png","timeStamp":1651168415865},{"screenshot":"ea471a0c0a0d90f023ea395e1ed1ddc1f16d82a692858fc71ccf4a9c937271db.png","timeStamp":1651168417302}],"result":"SUCCESS","precondition":false,"level":2},{"number":11,"description":"Student clicks on RadioButton","duration":2006,"startTime":"2022-04-28T12:53:37.457-05:00[America/Bogota]","screenshots":[{"screenshot":"4368a5aded901e9052f47ef7e67161b48c38d7ee326e12f02b04caa3f7380ac3.png","timeStamp":1651168418348},{"screenshot":"633e1305e35f537a05f661c88390d6c7c8cf67674dae7602658da287fa3fe8a6.png","timeStamp":1651168419462}],"result":"SUCCESS","precondition":false,"level":2},{"number":12,"description":"Student clicks on BtnNextHora","duration":2087,"startTime":"2022-04-28T12:53:39.583-05:00[America/Bogota]","screenshots":[{"screenshot":"4915b1717c78a4b8e93791db76659d614b07d3d5bb983e3dc0e2ef2c22df2429.png","timeStamp":1651168420429},{"screenshot":"96ab353e658f431c74cb0bda9b00766fadff2ad3d53307ca2d3af4386179203f.png","timeStamp":1651168421670}],"result":"SUCCESS","precondition":false,"level":2},{"number":13,"description":"Student enters \u0027Allan\u0027 into Nombre","duration":2384,"startTime":"2022-04-28T12:53:41.799-05:00[America/Bogota]","screenshots":[{"screenshot":"c72c50bcd3e42eee1713937e4b1f8fecb8f96d56169bc11be80b5c6acd2650b1.png","timeStamp":1651168422628},{"screenshot":"50618c0bf8fcb5668f7393af1c2ee70d367a3dac9feb50f6578502eb2a128e98.png","timeStamp":1651168424182}],"result":"SUCCESS","precondition":false,"level":2},{"number":14,"description":"Student enters \u0027Boyer\u0027 into Apellido","duration":2326,"startTime":"2022-04-28T12:53:44.302-05:00[America/Bogota]","screenshots":[{"screenshot":"805ea5e0fe3dc450d1332ad561a0a558f6de8bb1717c9493d6a4caffbac2e365.png","timeStamp":1651168425145},{"screenshot":"c594c303e192da540c873005847d231f4f1a249ba344dd5b57353cb5418a7147.png","timeStamp":1651168426628}],"result":"SUCCESS","precondition":false,"level":2},{"number":15,"description":"Student enters \u0027abraham.welch@yahoo.com\u0027 into Email","duration":2481,"startTime":"2022-04-28T12:53:46.757-05:00[America/Bogota]","screenshots":[{"screenshot":"2b31df81c616ce25971eab29d2a314307a6e925e44de45c34a703ba696d56dd3.png","timeStamp":1651168427557},{"screenshot":"fa23f48888692f7f03e46ad23135b292856901448ef93268b14007a4045d4d4a.png","timeStamp":1651168429238}],"result":"SUCCESS","precondition":false,"level":2},{"number":16,"description":"Student enters \u00276305012324\u0027 into Telefono","duration":2335,"startTime":"2022-04-28T12:53:49.360-05:00[America/Bogota]","screenshots":[{"screenshot":"fa23f48888692f7f03e46ad23135b292856901448ef93268b14007a4045d4d4a.png","timeStamp":1651168430177},{"screenshot":"eb7c04b15e5111b1001c113ba50d319d4baefab6a0acf2192b8106aa33f50ec0.png","timeStamp":1651168431695}],"result":"SUCCESS","precondition":false,"level":2},{"number":17,"description":"Student clicks on BtnNextContacto","duration":2059,"startTime":"2022-04-28T12:53:51.823-05:00[America/Bogota]","screenshots":[{"screenshot":"2df9de1b604c18b88ac95c3678a01a0f506312efd934e0cc2c62a7e166328bc7.png","timeStamp":1651168432634},{"screenshot":"fea6394a4e28a90c6c6cf064daa00854c44a56f0975a25bc61b4105ec52a1fb1.png","timeStamp":1651168433882}],"result":"SUCCESS","precondition":false,"level":2},{"number":18,"description":"Student enters \u0027husb3xvhou70u4hpsvoahtygkl6pw39d2qvrx2x429tmmrm06vpku6w86db1lv68vrbn2c54li8mip31ma4ko7suqcdh0wwcn1nv1ngdlscfhaosww2yunge67xdkd8rk0c8z9m6yt66k5xc95iuhawuenhvjvb2lg4h0nepc89yzvpnoxpt0xq4ceoxyxf8jlan4vecklhr5nen5cuyh3ldxynf8wtr0vjom9l0cgf9fqqcniddp1txyppb30x\u0027 into MensajePedido","duration":4766,"startTime":"2022-04-28T12:53:54.030-05:00[America/Bogota]","screenshots":[{"screenshot":"286479975c1a5ab317884c7a4211ad6c19e667754fdca2b8d338a2fa3dbc183b.png","timeStamp":1651168434897},{"screenshot":"6828233092d28f0a0ca94522bf9e7a6b8d1b15f10d4d111e6a51c91327b5f21e.png","timeStamp":1651168438796}],"result":"SUCCESS","precondition":false,"level":2},{"number":19,"description":"Student clicks on BtnNextContacto","duration":2295,"startTime":"2022-04-28T12:53:58.915-05:00[America/Bogota]","screenshots":[{"screenshot":"93462ceb19fa2279f4cb108f5d54def4ff7ab0e94d439d5655abaff04f6271e8.png","timeStamp":1651168439847},{"screenshot":"283a6d7221a748c74c4589ae6713676c687d695735d2bcf0130c09d931c73ac0.png","timeStamp":1651168441210}],"result":"SUCCESS","precondition":false,"level":2}]}]},{"number":20,"description":"Entonces debo observar que la reserva se ha creado satisfactoriamente","duration":1825,"startTime":"2022-04-28T12:54:01.991-05:00[America/Bogota]","screenshots":[{"screenshot":"d86c064db4f706e798362da89e2388c705ec0fc146d28d4b601d3d8333f5a38b.png","timeStamp":1651168443816}],"result":"SUCCESS","precondition":false,"level":0,"children":[{"number":21,"description":"Then el mensaje de reserva exitosa es  should be \u0027Reserva exitosa revise su correo para ver su codigo\u0027","duration":1666,"startTime":"2022-04-28T12:54:02.132-05:00[America/Bogota]","screenshots":[{"screenshot":"d86c064db4f706e798362da89e2388c705ec0fc146d28d4b601d3d8333f5a38b.png","timeStamp":1651168443798}],"result":"SUCCESS","precondition":false,"level":1}]}],"userStory":{"id":"validacion-de-campos-del-formulario","storyName":"Validacion de campos del formulario","path":"file:///E:/Sofka%20University/Automatizacion/FoodKa/src/test/resources/features/ValidarCamposReserva.feature","narrative":"  Yo como comensal\n  Requiero diligenciar un formulario con mi pedido\n  Para poder ordenar los platos que deseo","type":"feature"},"featureTag":{"name":"Features/Validacion de campos del formulario","type":"feature","displayName":"Features/Validacion de campos del formulario"},"title":"validar campos obligatorios completos","tags":[{"name":"Validacion de campos del formulario","type":"feature","displayName":"Validacion de campos del formulario"}],"startTime":"2022-04-28T12:53:18-05:00[America/Bogota]","duration":45818,"projectKey":"","sessionId":"e1d9431ce048e60bb610c5468c4a0d95","driver":"chrome","isManualTestingUpToDate":false,"manual":false,"testSource":"Cucumber","actors":[{"name":"Student","can":["browse the web"]}],"result":"SUCCESS"}